modules/__init__.py
modules/bsn.py
modules/passport.py
dutch_docs_validator-0.0.2.dist-info/METADATA
dutch_docs_validator-0.0.2.dist-info/WHEEL
dutch_docs_validator-0.0.2.dist-info/top_level.txt
dutch_docs_validator-0.0.2.dist-info/RECORD
