Metadata-Version: 2.1
Name: dutch-docs-validator
Version: 0.0.2
Summary: A basic dutch document validator
Home-page: UNKNOWN
Author: Ankit Gupta
Author-email: devankitgupta01@gmail.com
License: MIT
Keywords: dutch-docs-validator
Platform: UNKNOWN
Classifier: Development Status :: 5 - Production/Stable
Classifier: Operating System :: Microsoft :: Windows :: Windows 10
Classifier: License :: OSI Approved :: MIT License
Classifier: Programming Language :: Python :: 3
